wordlift_sdk/__init__.py
wordlift_sdk/client/__init__.py
wordlift_sdk/client/client_configuration_factory.py
wordlift_sdk/configuration/__init__.py
wordlift_sdk/configuration/configuration_provider.py
wordlift_sdk/configuration/get_config_value.py
wordlift_sdk/container/__init__.py
wordlift_sdk/container/application_container.py
wordlift_sdk/deprecated/__init__.py
wordlift_sdk/deprecated/create_entities_with_top_query_dataframe.py
wordlift_sdk/entity/__init__.py
wordlift_sdk/entity/enrich.py
wordlift_sdk/entity/patch.py
wordlift_sdk/google_search_console/__init__.py
wordlift_sdk/google_search_console/create_google_search_console_data_import.py
wordlift_sdk/google_search_console/raise_error_if_account_analytics_not_configured.py
wordlift_sdk/google_sheets/__init__.py
wordlift_sdk/google_sheets/google_sheets_lookup.py
wordlift_sdk/graph/graph_bag.py
wordlift_sdk/graph/ttl_liquid/__init__.py
wordlift_sdk/graph/ttl_liquid/ttl_liquid_graph_factory.py
wordlift_sdk/graphql/__init__.py
wordlift_sdk/graphql/client/__init__.py
wordlift_sdk/graphql/client/client.py
wordlift_sdk/graphql/client/factory.py
wordlift_sdk/graphql/client/gql_client_provider.py
wordlift_sdk/graphql/data/entities_by_type.graphql
wordlift_sdk/graphql/data/entities_embedding_value.graphql
wordlift_sdk/graphql/data/entities_top_query.graphql
wordlift_sdk/graphql/data/entities_url_id.graphql
wordlift_sdk/graphql/data/entities_url_iri.graphql
wordlift_sdk/graphql/data/entities_url_iri_with_source_equal_to_web_page_import.graphql
wordlift_sdk/graphql/query.py
wordlift_sdk/graphql/utils/__init__.py
wordlift_sdk/graphql/utils/query/__init__.py
wordlift_sdk/graphql/utils/query/entity_top_query.py
wordlift_sdk/graphql/utils/query/entity_with_top_query.py
wordlift_sdk/id_generator/__init__.py
wordlift_sdk/id_generator/id_generator.py
wordlift_sdk/id_generator/id_generator_interface.py
wordlift_sdk/internal_link/__init__.py
wordlift_sdk/internal_link/utils.py
wordlift_sdk/kg/__init__.py
wordlift_sdk/kg/entity.py
wordlift_sdk-2.10.1.dist-info/METADATA
wordlift_sdk-2.10.1.dist-info/WHEEL
wordlift_sdk-2.10.1.dist-info/RECORD
