Metadata-Version: 2.4
Name: wordlift-sdk
Version: 2.10.1
Summary: 
Author: David Riccitelli
Author-email: david@wordlift.io
Requires-Python: >=3.10,<3.14
Classifier: Programming Language :: Python :: 3
Classifier: Programming Language :: Python :: 3.10
Classifier: Programming Language :: Python :: 3.11
Classifier: Programming Language :: Python :: 3.12
Classifier: Programming Language :: Python :: 3.13
Requires-Dist: advertools (>0.16.6,<1.0.0)
Requires-Dist: aiohttp (>=3.10.5,<4.0.0)
Requires-Dist: google-auth (>=2.35.0,<3.0.0)
Requires-Dist: gql[aiohttp] (>=3.5.2,<4.0.0)
Requires-Dist: gspread (>=6.1.2,<7.0.0)
Requires-Dist: pandas (>=2.1.4,<2.3.0)
Requires-Dist: pycountry (>=24.6.1,<25.0.0)
Requires-Dist: python-liquid (>=2.0.1,<3.0.0)
Requires-Dist: rdflib (>=7.0.0,<8.0.0)
Requires-Dist: tenacity (>=9.0.0,<10.0.0)
Requires-Dist: tqdm (>=4.67.1,<5.0.0)
Requires-Dist: wordlift-client (>=1.133.0,<2.0.0)
